exdatetime/__init__.py
exdatetime/basics.py
exdatetime/funcs.py
exdatetime/julian.py
exdatetime-0.1.0.dist-info/LICENSE
exdatetime-0.1.0.dist-info/METADATA
exdatetime-0.1.0.dist-info/WHEEL
exdatetime-0.1.0.dist-info/top_level.txt
exdatetime-0.1.0.dist-info/RECORD
