Metadata-Version: 2.1
Name: exdatetime
Version: 0.1.0
Summary: Designed to extend from the module datetime of Python
Home-page: https://github.com/shenyouran/exdatetime
Author: ericoder
Author-email: ericshen0@yeah.net
License: UNKNOWN
Platform: UNKNOWN
License-File: LICENSE
